ctfd_downloader/__init__.py
ctfd_downloader/client.py
ctfd_downloader/config.py
ctfd_downloader/downloader.py
ctfd_downloader/main.py
ctfd_downloader/storage.py
tests/__init__.py
tests/test_client.py
tests/test_downloader.py
tests/test_storage.py
ctfd_dl-1.0.2.dist-info/METADATA
ctfd_dl-1.0.2.dist-info/WHEEL
ctfd_dl-1.0.2.dist-info/entry_points.txt
ctfd_dl-1.0.2.dist-info/top_level.txt
ctfd_dl-1.0.2.dist-info/RECORD
